mini_ipfabric/__init__.py
mini_ipfabric/client.py
mini_ipfabric/oas/__init__.py
mini_ipfabric/oas/v6.10.json
mini_ipfabric/oas/v7.0.json
mini_ipfabric/oas/v7.2.json
mini_ipfabric/oas/v7.3.json
mini_ipfabric/oas/v7.5.json
mini_ipfabric-7.5.0.dist-info/licenses/LICENSE
mini_ipfabric-7.5.0.dist-info/METADATA
mini_ipfabric-7.5.0.dist-info/WHEEL
mini_ipfabric-7.5.0.dist-info/RECORD
