Metadata-Version: 2.4
Name: mini-ipfabric
Version: 7.5.0
Summary: Mini Python package for interacting with IP Fabric using requests.
License: MIT
License-File: LICENSE
Keywords: ipfabric,ip-fabric,community-fabric
Author: Solution Architecture
Author-email: solution.architecture@ipfabric.io
Requires-Python: >=3.7,<4.0
Classifier: License :: OSI Approved :: MIT License
Classifier: Programming Language :: Python :: 3
Classifier: Programming Language :: Python :: 3.7
Classifier: Programming Language :: Python :: 3.8
Classifier: Programming Language :: Python :: 3.9
Classifier: Programming Language :: Python :: 3.10
Classifier: Programming Language :: Python :: 3.11
Classifier: Programming Language :: Python :: 3.12
Classifier: Programming Language :: Python :: 3.13
Classifier: Programming Language :: Python :: 3.14
Requires-Dist: importlib-metadata (==0.12) ; python_version < "3.8"
Requires-Dist: importlib_resources (>=5.0,<6.0) ; python_version < "3.9"
Requires-Dist: requests (>=2.31.0,<=2.33.0)
Project-URL: Homepage, https://gitlab.com/ip-fabric/integrations/mini-ipfabric
Project-URL: Repository, https://gitlab.com/ip-fabric/integrations/mini-ipfabric
